ezd/__init__.py
ezd/command.py
ezd/config.py
ezd/scrt.py
ezd/winsvc.py
ezd-0.3.2.dist-info/LICENSE
ezd-0.3.2.dist-info/METADATA
ezd-0.3.2.dist-info/WHEEL
ezd-0.3.2.dist-info/entry_points.txt
ezd-0.3.2.dist-info/top_level.txt
ezd-0.3.2.dist-info/RECORD
