Metadata-Version: 2.1
Name: ezd
Version: 0.3.2
Summary: Easy Deployment Tool
Home-page: https://github.com/koho/ezd
Author: Gerhard Tan
Author-email: gwohau.tan@gmail.com
License: MIT
Project-URL: Bug Tracker, https://github.com/koho/ezd/issues
Keywords: deploy,service,python-script,cli
Platform: any
Classifier: Environment :: Console
Classifier: License :: OSI Approved :: MIT License
Classifier: Programming Language :: Python
Classifier: Topic :: System :: Installation/Setup
Requires-Python: >=3.5
License-File: LICENSE
Requires-Dist: pywin32 ; sys_platform == "win32"
